bom_configuration-1.0.7-py3.8-nspkg.pth
bom/configuration/__init__.py
bom/configuration/bom.conf.json
bom/configuration/configtree.py
bom/configuration/constants.py
bom/configuration/environment.py
bom/configuration/py.typed
bom/configuration/utils.py
bom_configuration-1.0.7.dist-info/METADATA
bom_configuration-1.0.7.dist-info/WHEEL
bom_configuration-1.0.7.dist-info/namespace_packages.txt
bom_configuration-1.0.7.dist-info/top_level.txt
bom_configuration-1.0.7.dist-info/RECORD
