Metadata-Version: 2.1
Name: bom-configuration
Version: 1.0.7
Summary: Config fun.
Home-page: https://github.com/bomt1me/bomconfiguration
License: UNKNOWN
Platform: UNKNOWN
Requires-Python: >=3.8
